{
  "version": 3,
  "middleware": {
    "/": {
      "files": [
        "server/edge-runtime-webpack.js",
        "server/middleware.js"
      ],
      "name": "middleware",
      "page": "/",
      "matchers": [
        {
          "regexp": "^(?:\\/(_next\\/data\\/[^/]{1,}))?\\/classroom(?:\\/((?:[^\\/#\\?]+?)(?:\\/(?:[^\\/#\\?]+?))*))?(\\.json)?[\\/#\\?]?$",
          "originalSource": "/classroom/:path*"
        },
        {
          "regexp": "^(?:\\/(_next\\/data\\/[^/]{1,}))?\\/api\\/tutor(?:\\/((?:[^\\/#\\?]+?)(?:\\/(?:[^\\/#\\?]+?))*))?(\\.json)?[\\/#\\?]?$",
          "originalSource": "/api/tutor/:path*"
        },
        {
          "regexp": "^(?:\\/(_next\\/data\\/[^/]{1,}))?\\/api\\/chat(?:\\/((?:[^\\/#\\?]+?)(?:\\/(?:[^\\/#\\?]+?))*))?(\\.json)?[\\/#\\?]?$",
          "originalSource": "/api/chat/:path*"
        }
      ],
      "wasm": [
        {
          "name": "wasm_f4b69850bc2f6b02c2a186cea508d821c6b30f98",
          "filePath": "server/edge-chunks/wasm_f4b69850bc2f6b02c2a186cea508d821c6b30f98.wasm"
        }
      ],
      "assets": [],
      "env": {
        "__NEXT_BUILD_ID": "iGzdcBoj-d3dXh8e6Z2-Y",
        "NEXT_SERVER_ACTIONS_ENCRYPTION_KEY": "ysZN7PMxFvJ5/GvtEOa6vqafL88+YvN6rBsAwhMccHc=",
        "__NEXT_PREVIEW_MODE_ID": "1fdc5356eb8336a3cbdc7e847cf82792",
        "__NEXT_PREVIEW_MODE_SIGNING_KEY": "de0e47ecd1066b44a0d84393028d14c7e0e8a31d070fffba4dbcef8bbfefefbd",
        "__NEXT_PREVIEW_MODE_ENCRYPTION_KEY": "2ed5cfa7a56d9fa1c771c5400ae7d55d9176262c177ea215e5a71913410a6565"
      }
    }
  },
  "functions": {},
  "sortedMiddleware": [
    "/"
  ]
}